presencedb/__init__.py
presencedb/abc.py
presencedb/activity.py
presencedb/client.py
presencedb/constants.py
presencedb/enums.py
presencedb/errors.py
presencedb/user.py
presencedb/utils.py
presencedb-2.0.0.dist-info/AUTHORS.md
presencedb-2.0.0.dist-info/LICENSE
presencedb-2.0.0.dist-info/METADATA
presencedb-2.0.0.dist-info/WHEEL
presencedb-2.0.0.dist-info/top_level.txt
presencedb-2.0.0.dist-info/RECORD
